lego_store_availability/__init__.py
lego_store_availability/api.py
lego_store_availability/product.py
lego_store_availability/store.py
lego_store_availability/cache/__init__.py
lego_store_availability/cache/s3.py
lego_store_availability-0.2.0.dist-info/LICENSE.md
lego_store_availability-0.2.0.dist-info/METADATA
lego_store_availability-0.2.0.dist-info/WHEEL
lego_store_availability-0.2.0.dist-info/top_level.txt
lego_store_availability-0.2.0.dist-info/RECORD
