Metadata-Version: 2.1
Name: lego-store-availability
Version: 0.2.0
Summary: Check the availability of Lego™ product in stores
Home-page: https://github.com/Lunik/lego-store-availability
Author: Lunik
Author-email: lunik@tiwabbit.fr
Project-URL: Bug Tracker, https://github.com/Lunik/lego-store-availability/issues
Classifier: Programming Language :: Python :: 3
Classifier: License :: OSI Approved :: GNU General Public License v3 (GPLv3)
Classifier: Operating System :: OS Independent
Requires-Python: >=3.6
License-File: LICENSE.md
Requires-Dist: beautifulsoup4
Requires-Dist: requests
Requires-Dist: requests-cache
Requires-Dist: PyYAML
Provides-Extra: cache_s3
Requires-Dist: boto3 ; extra == 'cache_s3'
